torch_mlir_e2e_test/registry.py
torch_mlir_e2e_test/framework.py
torch_mlir_e2e_test/__init__.py
torch_mlir_e2e_test/utils.py
torch_mlir_e2e_test/annotations.py
torch_mlir_e2e_test/reporting.py
torch_mlir_e2e_test/mhlo_backends/__init__.py
torch_mlir_e2e_test/mhlo_backends/linalg_on_tensors.py
torch_mlir_e2e_test/mhlo_backends/abc.py
torch_mlir_e2e_test/linalg_on_tensors_backends/refbackend.py
torch_mlir_e2e_test/linalg_on_tensors_backends/__init__.py
torch_mlir_e2e_test/linalg_on_tensors_backends/abc.py
torch_mlir_e2e_test/tosa_backends/__init__.py
torch_mlir_e2e_test/tosa_backends/linalg_on_tensors.py
torch_mlir_e2e_test/tosa_backends/abc.py
torch_mlir_e2e_test/configs/lazy_tensor_core.py
torch_mlir_e2e_test/configs/torchdynamo.py
torch_mlir_e2e_test/configs/__init__.py
torch_mlir_e2e_test/configs/utils.py
torch_mlir_e2e_test/configs/linalg_on_tensors_backend.py
torch_mlir_e2e_test/configs/tosa_backend.py
torch_mlir_e2e_test/configs/torchscript.py
torch_mlir_e2e_test/configs/mhlo_backend.py
torch_mlir_e2e_test/configs/native_torch.py
torch_mlir_e2e_test/test_suite/matmul.py
torch_mlir_e2e_test/test_suite/cast.py
torch_mlir_e2e_test/test_suite/slice_like.py
torch_mlir_e2e_test/test_suite/return_types.py
torch_mlir_e2e_test/test_suite/reduction.py
torch_mlir_e2e_test/test_suite/custom_op_example.py
torch_mlir_e2e_test/test_suite/rng.py
torch_mlir_e2e_test/test_suite/scalar.py
torch_mlir_e2e_test/test_suite/norm_like.py
torch_mlir_e2e_test/test_suite/vision_models.py
torch_mlir_e2e_test/test_suite/pooling.py
torch_mlir_e2e_test/test_suite/elementwise.py
torch_mlir_e2e_test/test_suite/control_flow.py
torch_mlir_e2e_test/test_suite/__init__.py
torch_mlir_e2e_test/test_suite/argmax.py
torch_mlir_e2e_test/test_suite/quantized_models.py
torch_mlir_e2e_test/test_suite/mlp.py
torch_mlir_e2e_test/test_suite/threshold.py
torch_mlir_e2e_test/test_suite/reshape_like.py
torch_mlir_e2e_test/test_suite/type_conversion.py
torch_mlir-20221213.686.dist-info/RECORD
torch_mlir-20221213.686.dist-info/LICENSE
torch_mlir-20221213.686.dist-info/WHEEL
torch_mlir-20221213.686.dist-info/top_level.txt
torch_mlir-20221213.686.dist-info/METADATA
