Metadata-Version: 2.1
Name: torch-mlir
Version: 20221213.686
Summary: First-class interop between PyTorch and MLIR
Home-page: UNKNOWN
Author: Sean Silva
Author-email: silvasean@google.com
License: UNKNOWN
Platform: UNKNOWN
License-File: LICENSE
Requires-Dist: numpy
Requires-Dist: torch (==2.0.0.dev20221211)
